py_canalyzer.py
py_canalyzer_utils/app_utils/bus.py
py_canalyzer_utils/app_utils/capl.py
py_canalyzer_utils/app_utils/configuration.py
py_canalyzer_utils/app_utils/measurement.py
py_canalyzer_utils/app_utils/networks.py
py_canalyzer_utils/app_utils/performance.py
py_canalyzer_utils/app_utils/system.py
py_canalyzer_utils/app_utils/ui.py
py_canalyzer_utils/app_utils/version.py
py_canalyzer_utils/application.py
py_canalyzer_utils/py_logger.py
py_canalyzer-0.0.1.dist-info/LICENSE
py_canalyzer-0.0.1.dist-info/METADATA
py_canalyzer-0.0.1.dist-info/WHEEL
py_canalyzer-0.0.1.dist-info/RECORD
