Metadata-Version: 2.1
Name: py_canalyzer
Version: 0.0.1
Summary: Python CANalyzer Package
Home-page: https://github.com/chaitu-ycr/py_canalyzer.git
License: LICENSE
Keywords: Vector,CANalyzer,py_canalyzer
Author: chaitu-ycr
Author-email: chaitu.ycr@gmail.com
Requires-Python: >=3.8,<4.0
Classifier: License :: OSI Approved :: MIT License
Classifier: License :: Other/Proprietary License
Classifier: Operating System :: Microsoft :: Windows
Classifier: Programming Language :: Python :: 3
Classifier: Programming Language :: Python :: 3.8
Classifier: Programming Language :: Python :: 3.9
Classifier: Programming Language :: Python :: 3.10
Classifier: Programming Language :: Python :: 3.11
Classifier: Programming Language :: Python :: 3.12
Classifier: Topic :: Software Development :: Embedded Systems
Requires-Dist: pytest-html (>=4.1.1,<5.0.0)
Requires-Dist: pywin32 (>=306,<307)
Project-URL: Documentation, https://chaitu-ycr.github.io/py_canalyzer/
Project-URL: Repository, https://github.com/chaitu-ycr/py_canalyzer.git
